dotfiles_manager/__init__.py
dotfiles_manager/__main__.py
dotfiles_manager/commands/__init__.py
dotfiles_manager/commands/copy.py
dotfiles_manager/commands/init.py
dotfiles_manager/commands/runner.py
dotfiles_manager/commands/script.py
dotfiles_manager/commands/symlink.py
dotfiles_manager/utils/__init__.py
dotfiles_manager/utils/config.py
dotfiles_manager/utils/exception.py
dotfiles_manager/utils/logger.py
dotfiles_manager/utils/style.py
dotfiles_manager/utils/template.py
dotfiles_manager/utils/fs/__init__.py
dotfiles_manager/utils/fs/base.py
dotfiles_manager/utils/fs/condition.py
dotfiles_manager/utils/fs/flags.py
dotfiles_manager/utils/fs/fs.py
dotfiles_manager/utils/fs/log.py
dotfiles_manager/utils/fs/path.py
dotfiles_manager/utils/fs/shell.py
manager_dotfiles-0.1.0.dist-info/licenses/LICENSE
manager_dotfiles-0.1.0.dist-info/METADATA
manager_dotfiles-0.1.0.dist-info/WHEEL
manager_dotfiles-0.1.0.dist-info/entry_points.txt
manager_dotfiles-0.1.0.dist-info/top_level.txt
manager_dotfiles-0.1.0.dist-info/RECORD
