Metadata-Version: 2.4
Name: manager-dotfiles
Version: 0.1.0
Summary: dotfiles manager for link/copy files, and run backup/refresh scripts
Author-email: rgermain <contact@germainremi.fr>
License: MIT License
Project-URL: projects, https://github.com/remigermain/manager-dotfiles
Classifier: Development Status :: 5 - Production/Stable
Classifier: Programming Language :: Python
Classifier: Programming Language :: Python :: 3 :: Only
Classifier: Programming Language :: Python :: 3.9
Classifier: Programming Language :: Python :: 3.10
Classifier: Programming Language :: Python :: 3.11
Classifier: Programming Language :: Python :: 3.12
Classifier: Programming Language :: Python :: 3.13
Requires-Python: >=3.9
License-File: LICENSE
Requires-Dist: jinja2>=3.1.6
Dynamic: license-file
